Metadata-Version: 2.1
Name: inmanta-tfplugin
Version: 5.2.0
Summary: Auto generated python package for Terraform Plugin RPC protocol
Home-page: https://github.com/inmanta/inmanta-tfplugin
Author: Inmanta
Author-email: code@inmanta.com
License: MPL 2.0
Platform: UNKNOWN
Classifier: Development Status :: 5 - Production/Stable
Classifier: Intended Audience :: Developers
Classifier: Operating System :: OS Independent
Classifier: Topic :: Software Development
Classifier: Programming Language :: Python :: 3.5
Classifier: Programming Language :: Python :: 3.6
Classifier: Programming Language :: Python :: 3.7
Classifier: Programming Language :: Python :: 3.9
Requires-Python: >=3.6
License-File: LICENSE
